pubmed_fetcher/__init__.py
pubmed_fetcher/cli.py
pubmed_fetcher/pubmed_api.py
pubmed_fetcher_abhichandra-0.1.5.dist-info/entry_points.txt
pubmed_fetcher_abhichandra-0.1.5.dist-info/LICENSE
pubmed_fetcher_abhichandra-0.1.5.dist-info/METADATA
pubmed_fetcher_abhichandra-0.1.5.dist-info/WHEEL
pubmed_fetcher_abhichandra-0.1.5.dist-info/RECORD
