Metadata-Version: 2.3
Name: pubmed-fetcher-abhichandra
Version: 0.1.5
Summary: A Python package to fetch research papers from PubMed
License: MIT
Author: abhichandra
Author-email: abhichandrav108@gmail.com
Requires-Python: >=3.13
Classifier: License :: OSI Approved :: MIT License
Classifier: Programming Language :: Python :: 3
Classifier: Programming Language :: Python :: 3.13
Requires-Dist: requests (>=2.32.3,<3.0.0)
Project-URL: Repository, https://github.com/iwilldefinitelybecoder/pubmed-fetcher
